freezer_api/__init__.py
freezer_api/context.py
freezer_api/policy.py
freezer_api/service.py
freezer_api/api/__init__.py
freezer_api/api/versions.py
freezer_api/api/common/__init__.py
freezer_api/api/common/middleware.py
freezer_api/api/common/resource.py
freezer_api/api/common/utils.py
freezer_api/api/v1/__init__.py
freezer_api/api/v1/actions.py
freezer_api/api/v1/backups.py
freezer_api/api/v1/clients.py
freezer_api/api/v1/homedoc.py
freezer_api/api/v1/jobs.py
freezer_api/api/v1/sessions.py
freezer_api/api/v2/__init__.py
freezer_api/api/v2/actions.py
freezer_api/api/v2/backups.py
freezer_api/api/v2/clients.py
freezer_api/api/v2/homedoc.py
freezer_api/api/v2/jobs.py
freezer_api/api/v2/sessions.py
freezer_api/cmd/__init__.py
freezer_api/cmd/api.py
freezer_api/cmd/manage.py
freezer_api/cmd/status.py
freezer_api/cmd/wsgi.py
freezer_api/common/__init__.py
freezer_api/common/_i18n.py
freezer_api/common/check.py
freezer_api/common/config.py
freezer_api/common/db_mappings.py
freezer_api/common/elasticv2_utils.py
freezer_api/common/exceptions.py
freezer_api/common/json_schemas.py
freezer_api/common/utils.py
freezer_api/common/policies/__init__.py
freezer_api/common/policies/action.py
freezer_api/common/policies/backup.py
freezer_api/common/policies/base.py
freezer_api/common/policies/client.py
freezer_api/common/policies/job.py
freezer_api/common/policies/session.py
freezer_api/db/__init__.py
freezer_api/db/base.py
freezer_api/db/common.py
freezer_api/db/manager.py
freezer_api/db/elasticsearch/__init__.py
freezer_api/db/elasticsearch/driver.py
freezer_api/db/elasticsearch/es_manager.py
freezer_api/db/sqlalchemy/__init__.py
freezer_api/db/sqlalchemy/alembic.ini
freezer_api/db/sqlalchemy/api.py
freezer_api/db/sqlalchemy/driver.py
freezer_api/db/sqlalchemy/models.py
freezer_api/db/sqlalchemy/migrations/README
freezer_api/db/sqlalchemy/migrations/env.py
freezer_api/db/sqlalchemy/migrations/script.py.mako
freezer_api-17.0.0.dist-info/AUTHORS
freezer_api-17.0.0.dist-info/LICENSE
freezer_api-17.0.0.dist-info/METADATA
freezer_api-17.0.0.dist-info/WHEEL
freezer_api-17.0.0.dist-info/entry_points.txt
freezer_api-17.0.0.dist-info/pbr.json
freezer_api-17.0.0.dist-info/top_level.txt
freezer_api-17.0.0.dist-info/RECORD
