Metadata-Version: 2.1
Name: freezer-api
Version: 17.0.0
Summary: OpenStack Backup and Restore API Service
Home-page: https://docs.openstack.org/freezer/latest/
Author: OpenStack
Author-email: openstack-discuss@lists.openstack.org
License: Apache-2.0
Classifier: Environment :: OpenStack
Classifier: Programming Language :: Python
Classifier: Programming Language :: Python :: Implementation :: CPython
Classifier: Programming Language :: Python :: 3 :: Only
Classifier: Programming Language :: Python :: 3
Classifier: Programming Language :: Python :: 3.8
Classifier: Programming Language :: Python :: 3.9
Classifier: Development Status :: 5 - Production/Stable
Classifier: Natural Language :: English
Classifier: Intended Audience :: Developers
Classifier: Intended Audience :: Financial and Insurance Industry
Classifier: Intended Audience :: Information Technology
Classifier: Intended Audience :: System Administrators
Classifier: Intended Audience :: Telecommunications Industry
Classifier: Operating System :: MacOS
Classifier: Operating System :: POSIX :: BSD :: FreeBSD
Classifier: Operating System :: POSIX :: BSD :: NetBSD
Classifier: Operating System :: POSIX :: BSD :: OpenBSD
Classifier: Operating System :: POSIX :: Linux
Classifier: Operating System :: Unix
Classifier: Topic :: System :: Archiving :: Backup
Classifier: Topic :: System :: Archiving :: Compression
Classifier: Topic :: System :: Archiving
Requires-Python: >=3.8
License-File: LICENSE
License-File: AUTHORS
Requires-Dist: elasticsearch <3.0.0,>=2.0.0
Requires-Dist: falcon >=1.0.0
Requires-Dist: jsonschema >=3.2.0
Requires-Dist: keystonemiddleware >=4.17.0
Requires-Dist: Paste >=2.0.2
Requires-Dist: PasteDeploy >=1.5.0
Requires-Dist: oslo.config >=6.8.0
Requires-Dist: oslo.context >=2.22.0
Requires-Dist: oslo.db >=4.44.0
Requires-Dist: oslo.i18n >=3.15.3
Requires-Dist: oslo.log >=3.36.0
Requires-Dist: oslo.middleware >=3.31.0
Requires-Dist: oslo.policy >=4.5.0
Requires-Dist: oslo.serialization >=2.25.0
Requires-Dist: oslo.upgradecheck >=1.3.0
Requires-Dist: SQLAlchemy >=1.2.19
Requires-Dist: alembic >=1.8.0
